plone.protect-5.0.5-py3.13-nspkg.pth
plone/protect/__init__.py
plone/protect/authenticator.py
plone/protect/auto.py
plone/protect/configure.zcml
plone/protect/confirm.pt
plone/protect/interfaces.py
plone/protect/monkey.py
plone/protect/postonly.py
plone/protect/protect.js
plone/protect/subscribers.py
plone/protect/testing.py
plone/protect/utils.py
plone/protect/views.py
plone/protect/profiles/default/metadata.xml
plone/protect/tests/__init__.py
plone/protect/tests/case.py
plone/protect/tests/test.zcml
plone/protect/tests/testAuthenticator.py
plone/protect/tests/testAuto.py
plone/protect/tests/testPatches.py
plone/protect/tests/testPostOnly.py
plone/protect/tests/testUtils.py
plone/protect/tests/test_confirm_view.py
plone_protect-5.0.5.dist-info/METADATA
plone_protect-5.0.5.dist-info/WHEEL
plone_protect-5.0.5.dist-info/namespace_packages.txt
plone_protect-5.0.5.dist-info/top_level.txt
plone_protect-5.0.5.dist-info/RECORD
